multiplier/__init__.py
multiplier/multipy_two_numbers.py
multiplier-0.1.1.dist-info/METADATA
multiplier-0.1.1.dist-info/WHEEL
multiplier-0.1.1.dist-info/top_level.txt
multiplier-0.1.1.dist-info/RECORD
