Metadata-Version: 2.1
Name: multiplier
Version: 0.1.1
Summary: Multiplier library
Home-page: https://multiplier.readthedocs.io/
Author: John Robert
Author-email: condo@gmail.com
License: UNKNOWN
Platform: UNKNOWN
Requires-Dist: numpy
